py_windows_exe/__init__.py
py_windows_exe-1.0.0.dist-info/DESCRIPTION.rst
py_windows_exe-1.0.0.dist-info/METADATA
py_windows_exe-1.0.0.dist-info/RECORD
py_windows_exe-1.0.0.dist-info/WHEEL
py_windows_exe-1.0.0.dist-info/metadata.json
py_windows_exe-1.0.0.dist-info/top_level.txt
