Metadata-Version: 2.0
Name: py-windows-exe
Version: 1.0.0
Summary: Functions needed when running a Python program as a Windows exe
Home-page: https://github.com/bodylabs/py_windows_exe
Author: Body Labs
Author-email: alex@bodylabs.com
License: MIT
Platform: UNKNOWN
Classifier: Development Status :: 3 - Alpha
Classifier: Intended Audience :: Developers
Classifier: License :: OSI Approved :: BSD License
Classifier: Operating System :: OS Independent
Classifier: Programming Language :: Python
